[
	{ "id": "14", "name": "Отопление", "techpstid": "" },
	{
		"id": "24",
		"name": "Погружные колодезные насосы SB, SB HF и SBA",
		"techpstid": ""
	},
	{ "id": "56", "name": "Скважинные насосы SP A 3x400В", "techpstid": "" },
	{ "id": "29", "name": "Скважинные насосы SQ", "techpstid": "" },
	{ "id": "22", "name": "Водоснабжение", "techpstid": "" },
	{ "id": "23", "name": "Дренаж и канализация", "techpstid": "" },
	{
		"id": "27",
		"name": "Канализационные насосные установки MULTILIFT",
		"techpstid": ""
	},
	{ "id": "30", "name": "Циркуляционные насосы ALPHA2 old", "techpstid": "" },
	{ "id": "31", "name": "Циркуляционные насосы ALPHA2 L old", "techpstid": "" },
	{ "id": "32", "name": "Циркуляционные насосы SOLAR", "techpstid": "" },
	{
		"id": "33",
		"name": "Циркуляционные насосы UPS со штуцером для воздухоотводчика",
		"techpstid": ""
	},
	{ "id": "34", "name": "Циркуляционные насосы UP", "techpstid": "" },
	{
		"id": "35",
		"name": "Циркуляционные насосы COMFORT для систем ГВС",
		"techpstid": ""
	},
	{ "id": "36", "name": "Скважинные насосы SQE", "techpstid": "" },
	{ "id": "38", "name": "Скважинные насосы SP A 1x230В", "techpstid": "" },
	{
		"id": "39",
		"name": "Миниатюрные насосы повышения давления UPA",
		"techpstid": ""
	},
	{
		"id": "40",
		"name": "Самовсасывающие насосные установки водоснабжения MQ",
		"techpstid": ""
	},
	{ "id": "41", "name": "Самовсасывающие насосы JP", "techpstid": "" },
	{
		"id": "42",
		"name": "Самовсасывающие насосные установки водоснабжения JPB",
		"techpstid": ""
	},
	{ "id": "44", "name": "Дренажные насосы UNILIFT CC", "techpstid": "" },
	{ "id": "45", "name": "Дренажные насосы UNILIFT KP", "techpstid": "" },
	{
		"id": "46",
		"name": "Дренажные насосы UNILIFT AP 12, AP 35, AP 50",
		"techpstid": ""
	},
	{
		"id": "47",
		"name": "Дренажные насосы UNILIFT AP 35B, AP 50B",
		"techpstid": ""
	},
	{ "id": "48", "name": "Накопительные емкости LIFTAWAY", "techpstid": "" },
	{
		"id": "51",
		"name": "Канализационные насосные установки SOLOLIFT2",
		"techpstid": ""
	},
	{
		"id": "50",
		"name": "Насосная установка для отвода конденсата CONLIFT1",
		"techpstid": ""
	},
	{ "id": "55", "name": "Циркуляционные насосы UPS", "techpstid": "" },
	{ "id": "57", "name": "Принадлежности", "techpstid": "" },
	{ "id": "59", "name": "Автоматика", "techpstid": "" },
	{ "id": "60", "name": "Аксессуары", "techpstid": "" },
	{ "id": "61", "name": "Скважинные насосы SQ с кабелем", "techpstid": "" },
	{ "id": "62", "name": "Скважинные насосы SQE - комплект", "techpstid": "" },
	{
		"id": "63",
		"name": "Насосные установки CMBE повышения давления со встроенным преобразователем частоты",
		"techpstid": ""
	},
	{
		"id": "64",
		"name": "Насосные установки самовсасывающего типа CMB-SP SET",
		"techpstid": ""
	},
	{
		"id": "65",
		"name": "Насосные установки повышения давления CMB",
		"techpstid": ""
	},
	{ "id": "66", "name": "Циркуляционные насосы MAGNA1", "techpstid": "" },
	{ "id": "67", "name": "Циркуляционные насосы MAGNA3", "techpstid": "" },
	{ "id": "68", "name": "Циркуляционные насосы ALPHA3 old", "techpstid": "" },
	{
		"id": "69",
		"name": "Cамовсасывающая насосная установка SCALA2",
		"techpstid": ""
	},
	{ "id": "70", "name": "Погружные дренажные насосы KPC", "techpstid": "" },
	{ "id": "71", "name": "Насосы для водоснабжения NS и PF", "techpstid": "" },
	{ "id": "72", "name": "Насосные группы HEATMIX", "techpstid": "" },
	{
		"id": "73",
		"name": "Самовсасывающие насосные установки водоснабжения JPA PT",
		"techpstid": ""
	},
	{
		"id": "74",
		"name": "Самовсасывающие насосные установки водоснабжения с внешним эжектором JPD PT",
		"techpstid": ""
	},
	{
		"id": "75",
		"name": "Принадлежности для насосных групп HEATMIX",
		"techpstid": ""
	},
	{ "id": "76", "name": "Циркуляционные насосы ALPHA SOLAR", "techpstid": "" },
	{
		"id": "77",
		"name": "Насосные установки повышения давления CMBE TWIN",
		"techpstid": ""
	},
	{ "id": "78", "name": "Циркуляционные насосы ALPHA3", "techpstid": "" },
	{ "id": "79", "name": "Циркуляционные насосы ALPHA2", "techpstid": "" },
	{ "id": "80", "name": "Циркуляционные насосы ALPHA1 L", "techpstid": "" },
	{ "id": "83", "name": "Мембранные напорные баки", "techpstid": "" },
	{
		"id": "86",
		"name": "Самовсасывающие насосные установки JP PT",
		"techpstid": ""
	},
	{
		"id": "87",
		"name": "Принадлежности для насосных установок CMBE TWIN",
		"techpstid": ""
	},
	{
		"id": "93",
		"name": "Cамовсасывающая насосная установка SCALA1",
		"techpstid": ""
	},
	{
		"id": "94",
		"name": "Принадлежности для насосных установок SCALA1",
		"techpstid": ""
	},
	{ "id": "95", "name": "Канализацонные насосы SEG", "techpstid": "" }
]
